<?xml version="1.0" encoding="utf-8"?>
<modification>
    <name>d_social_login</name>
    <code>d_social_login</code>
    <description>Social Login</description>
    <version>5.0.0</version>
    <author>Dreamwention Team</author>
    <link>http://www.dreamvention.ee/</link>

        <file path="admin/model/customer/customer.php">
            <operation error="skip">
                <search><![CDATA[$this->db->query("DELETE FROM " . DB_PREFIX . "customer WHERE customer_id = '" . (int)$customer_id . "'");]]></search>
                <add position="after"><![CDATA[$this->db->query("DELETE FROM " . DB_PREFIX . "customer_authentication WHERE customer_id = '" . (int)$customer_id . "'");]]></add>
            </operation>
        </file>

        <file path="admin/model/sale/customer.php">
            <operation error="skip">
                <search><![CDATA[$this->db->query("DELETE FROM " . DB_PREFIX . "customer WHERE customer_id = '" . (int)$customer_id . "'");]]></search>
                <add position="after"><![CDATA[$this->db->query("DELETE FROM " . DB_PREFIX . "customer_authentication WHERE customer_id = '" . (int)$customer_id . "'");]]></add>
            </operation>
        </file>


</modification>
